doprompt/__init__.py
doprompt/doprompt.py
doprompt-0.1.2.dist-info/LICENSE
doprompt-0.1.2.dist-info/METADATA
doprompt-0.1.2.dist-info/WHEEL
doprompt-0.1.2.dist-info/top_level.txt
doprompt-0.1.2.dist-info/RECORD
