Metadata-Version: 2.2
Name: doprompt
Version: 0.1.2
Summary: Add your description here
Requires-Python: >=3.10
License-File: LICENSE
Requires-Dist: pybars3>=0.9.7
Requires-Dist: pyyaml>=6.0.2
